{ "frames": [
   {
    "filename": "pornulak 0.aseprite",
    "frame": { "x": 0, "y": 0, "w": 32, "h": 33 },
    "rotated": false,
    "trimmed": false,
    "spriteSourceSize": { "x": 0, "y": 0, "w": 32, "h": 33 },
    "sourceSize": { "w": 32, "h": 33 },
    "duration": 80
   },
   {
    "filename": "pornulak 1.aseprite",
    "frame": { "x": 32, "y": 0, "w": 32, "h": 33 },
    "rotated": false,
    "trimmed": false,
    "spriteSourceSize": { "x": 0, "y": 0, "w": 32, "h": 33 },
    "sourceSize": { "w": 32, "h": 33 },
    "duration": 80
   },
   {
    "filename": "pornulak 2.aseprite",
    "frame": { "x": 64, "y": 0, "w": 32, "h": 33 },
    "rotated": false,
    "trimmed": false,
    "spriteSourceSize": { "x": 0, "y": 0, "w": 32, "h": 33 },
    "sourceSize": { "w": 32, "h": 33 },
    "duration": 80
   },
   {
    "filename": "pornulak 3.aseprite",
    "frame": { "x": 96, "y": 0, "w": 32, "h": 33 },
    "rotated": false,
    "trimmed": false,
    "spriteSourceSize": { "x": 0, "y": 0, "w": 32, "h": 33 },
    "sourceSize": { "w": 32, "h": 33 },
    "duration": 80
   },
   {
    "filename": "pornulak 4.aseprite",
    "frame": { "x": 128, "y": 0, "w": 32, "h": 33 },
    "rotated": false,
    "trimmed": false,
    "spriteSourceSize": { "x": 0, "y": 0, "w": 32, "h": 33 },
    "sourceSize": { "w": 32, "h": 33 },
    "duration": 80
   },
   {
    "filename": "pornulak 5.aseprite",
    "frame": { "x": 160, "y": 0, "w": 32, "h": 33 },
    "rotated": false,
    "trimmed": false,
    "spriteSourceSize": { "x": 0, "y": 0, "w": 32, "h": 33 },
    "sourceSize": { "w": 32, "h": 33 },
    "duration": 80
   },
   {
    "filename": "pornulak 6.aseprite",
    "frame": { "x": 192, "y": 0, "w": 32, "h": 33 },
    "rotated": false,
    "trimmed": false,
    "spriteSourceSize": { "x": 0, "y": 0, "w": 32, "h": 33 },
    "sourceSize": { "w": 32, "h": 33 },
    "duration": 80
   },
   {
    "filename": "pornulak 7.aseprite",
    "frame": { "x": 224, "y": 0, "w": 32, "h": 33 },
    "rotated": false,
    "trimmed": false,
    "spriteSourceSize": { "x": 0, "y": 0, "w": 32, "h": 33 },
    "sourceSize": { "w": 32, "h": 33 },
    "duration": 80
   },
   {
    "filename": "pornulak 8.aseprite",
    "frame": { "x": 256, "y": 0, "w": 32, "h": 33 },
    "rotated": false,
    "trimmed": false,
    "spriteSourceSize": { "x": 0, "y": 0, "w": 32, "h": 33 },
    "sourceSize": { "w": 32, "h": 33 },
    "duration": 80
   },
   {
    "filename": "pornulak 9.aseprite",
    "frame": { "x": 288, "y": 0, "w": 32, "h": 33 },
    "rotated": false,
    "trimmed": false,
    "spriteSourceSize": { "x": 0, "y": 0, "w": 32, "h": 33 },
    "sourceSize": { "w": 32, "h": 33 },
    "duration": 80
   },
   {
    "filename": "pornulak 10.aseprite",
    "frame": { "x": 320, "y": 0, "w": 32, "h": 33 },
    "rotated": false,
    "trimmed": false,
    "spriteSourceSize": { "x": 0, "y": 0, "w": 32, "h": 33 },
    "sourceSize": { "w": 32, "h": 33 },
    "duration": 80
   }
 ],
 "meta": {
  "app": "http://www.aseprite.org/",
  "version": "1.3.17-x64",
  "image": "pornulak.png",
  "format": "RGBA8888",
  "size": { "w": 352, "h": 33 },
  "scale": "1",
  "frameTags": [
  ]
 }
}
